README.md
setup.py
chronicler/__init__.py
chronicler/decorators.py
chronicler/models.py
chronicler/utils.py
chronicler.egg-info/PKG-INFO
chronicler.egg-info/SOURCES.txt
chronicler.egg-info/dependency_links.txt
chronicler.egg-info/not-zip-safe
chronicler.egg-info/top_level.txt
chronicler/migrations/0001_initial.py
chronicler/migrations/__init__.py
chronicler/tests/__init__.py
chronicler/tests/models.py
chronicler/tests/test_audit_decorator.py
chronicler/tests/test_create_audit.py
chronicler/tests/migrations/0001_initial.py
chronicler/tests/migrations/__init__.py