Metadata-Version: 1.1
Name: chronicler
Version: 0.3
Summary: A Django App for preserving revisions of modified Model Objects
Home-page: http://github.com/analytehealth/chronicler
Author: Analyte Health
Author-email: open-source@analytehealth.com
License: UNKNOWN
Platform: UNKNOWN
Classifier: Framework :: Django
Classifier: Intended Audience :: Developers
Classifier: Operating System :: OS Independent
Classifier: Topic :: Software Development
